pywal/__init__.py
pywal/__main__.py
pywal/colors.py
pywal/donation.py
pywal/eastereggs.py
pywal/export.py
pywal/image.py
pywal/reload.py
pywal/sequences.py
pywal/settings.py
pywal/theme.py
pywal/util.py
pywal/wallpaper.py
pywal/backends/__init__.py
pywal/backends/colorthief.py
pywal/backends/colorz.py
pywal/backends/fast_colorthief.py
pywal/backends/haishoku.py
pywal/backends/modern_colorthief.py
pywal/backends/okthief.py
pywal/backends/schemer2.py
pywal/backends/wal.py
pywal/colorschemes/dark/3024.json
pywal/colorschemes/dark/ashes.json
pywal/colorschemes/dark/base16-3024.json
pywal/colorschemes/dark/base16-apathy.json
pywal/colorschemes/dark/base16-ashes.json
pywal/colorschemes/dark/base16-atelier-cave.json
pywal/colorschemes/dark/base16-atelier-dune.json
pywal/colorschemes/dark/base16-atelier-estuary.json
pywal/colorschemes/dark/base16-atelier-forest.json
pywal/colorschemes/dark/base16-atelier-heath.json
pywal/colorschemes/dark/base16-atelier-lakeside.json
pywal/colorschemes/dark/base16-atelier-plateau.json
pywal/colorschemes/dark/base16-atelier-savanna.json
pywal/colorschemes/dark/base16-atelier-seaside.json
pywal/colorschemes/dark/base16-atelier-sulphurpool.json
pywal/colorschemes/dark/base16-bespin.json
pywal/colorschemes/dark/base16-black-metal-bathory.json
pywal/colorschemes/dark/base16-black-metal-burzum.json
pywal/colorschemes/dark/base16-black-metal-funeral.json
pywal/colorschemes/dark/base16-black-metal-gorgoroth.json
pywal/colorschemes/dark/base16-black-metal-immortal.json
pywal/colorschemes/dark/base16-black-metal-khold.json
pywal/colorschemes/dark/base16-black-metal-marduk.json
pywal/colorschemes/dark/base16-black-metal-mayhem.json
pywal/colorschemes/dark/base16-black-metal-nile.json
pywal/colorschemes/dark/base16-black-metal-venom.json
pywal/colorschemes/dark/base16-black-metal.json
pywal/colorschemes/dark/base16-brewer.json
pywal/colorschemes/dark/base16-bright.json
pywal/colorschemes/dark/base16-brushtrees.json
pywal-3.8.14.dist-info/licenses/LICENSE.md
pywal-3.8.14.dist-info/METADATA
pywal-3.8.14.dist-info/WHEEL
pywal-3.8.14.dist-info/entry_points.txt
pywal-3.8.14.dist-info/top_level.txt
pywal-3.8.14.dist-info/RECORD
